cheru/__init__.py
cheru-1.0.dist-info/METADATA
cheru-1.0.dist-info/WHEEL
cheru-1.0.dist-info/top_level.txt
cheru-1.0.dist-info/RECORD
