Metadata-Version: 2.1
Name: cheru
Version: 1.0
Summary: This pakage helps the user to download reviews from amazon and flipkart . created by chetan
Home-page: UNKNOWN
Author: Chetan
License: UNKNOWN
Platform: UNKNOWN
Requires-Dist: pandas
Requires-Dist: numpy
Requires-Dist: requests
Requires-Dist: textblob
Requires-Dist: bs4
Requires-Dist: matplotlib
Requires-Dist: nltk
Requires-Dist: seaborn
